core/__init__.py
ActionsToolkit-0.0.2.dist-info/LICENSE
ActionsToolkit-0.0.2.dist-info/METADATA
ActionsToolkit-0.0.2.dist-info/WHEEL
ActionsToolkit-0.0.2.dist-info/top_level.txt
ActionsToolkit-0.0.2.dist-info/RECORD
