Metadata-Version: 2.1
Name: ActionsToolkit
Version: 0.0.2
Summary: A Python toolkit for building GitHub Actions
Home-page: https://github.com/yanglbme/actions-toolkit
Author: yanglbme
Author-email: contact@yanglibin.info
License: UNKNOWN
Platform: UNKNOWN
Classifier: Programming Language :: Python :: 3
Classifier: License :: OSI Approved :: MIT License
Classifier: Operating System :: OS Independent
Requires-Python: >=3.6
